{
  "count": 121,
  "uniques": 80,
  "clones": [
    {
      "timestamp": "2026-01-23T00:00:00Z",
      "count": 12,
      "uniques": 9
    },
    {
      "timestamp": "2026-01-24T00:00:00Z",
      "count": 21,
      "uniques": 10
    },
    {
      "timestamp": "2026-01-25T00:00:00Z",
      "count": 14,
      "uniques": 9
    },
    {
      "timestamp": "2026-01-26T00:00:00Z",
      "count": 22,
      "uniques": 15
    },
    {
      "timestamp": "2026-01-27T00:00:00Z",
      "count": 16,
      "uniques": 12
    },
    {
      "timestamp": "2026-01-28T00:00:00Z",
      "count": 18,
      "uniques": 12
    },
    {
      "timestamp": "2026-01-29T00:00:00Z",
      "count": 18,
      "uniques": 13
    }
  ]
}